cli/account.py
cli/ask.py
cli/configure.py
cli/connection.py
cli/database.py
cli/io.py
cli/keypair.py
cli/main.py
cli/recommend.py
cli/schema.py
cli/scrape.py
cli/security.py
cli/sql.py
cli/table.py
cli/warehouse.py
cli/core/constants.py
cli/core/fs.py
cli/core/logging.py
cli/core/config/parser.py
cli/core/config/sfcli.py
cli/core/security/hunt.py
cli/core/security/runner.py
cli/core/security/types.py
cli/core/security/hunt_definitions/snowflake_unc5537_breach.py
cli/core/security/playbooks/benchmarks.py
cli/core/security/playbooks/unc5537_breach.py
cli/core/snowflake/connection.py
cli/core/snowflake/query.py
cli/core/snowflake/sql.py
cli/core/util/key.py
cli/core/util/time.py
snowflakecli-0.4.4.dist-info/METADATA
snowflakecli-0.4.4.dist-info/WHEEL
snowflakecli-0.4.4.dist-info/entry_points.txt
snowflakecli-0.4.4.dist-info/top_level.txt
snowflakecli-0.4.4.dist-info/RECORD
