Metadata-Version: 2.1
Name: snowflakecli
Version: 0.4.4
Summary: A DuckDB-powered command line interface for Snowflake security, governance, operations, and cost optimization.
Author-email: jake <jake@bostata.com>
License: MIT
Requires-Python: ==3.11.*
Requires-Dist: duckdb>=1.0.0
Requires-Dist: snowflake-connector-python>=3.11.0
Requires-Dist: typer>=0.12.3
Requires-Dist: datafusion>=38.0.0
Requires-Dist: loguru>=0.7.2
Requires-Dist: pyperclip>=1.9.0
Provides-Extra: dev
Requires-Dist: ipython>=8.25.0; extra == "dev"
Requires-Dist: black>=24.4.2; extra == "dev"
Requires-Dist: pylint>=3.2.6; extra == "dev"
Requires-Dist: ruff>=0.6.1; extra == "dev"
